<?xml version="1.0" encoding="utf-8"?>
<ArrayOfCall xmlns:xsi="http://www.w3.org/2001/XMLSchema-instance" xmlns:xsd="http://www.w3.org/2001/XMLSchema">
  <Call>
    <Id>1000</Id>
    <CallType>Food</CallType>
    <FullAddress>123 Main Street</FullAddress>
    <Latitude>60.26057379682209</Latitude>
    <Longitude>-56.47349417774127</Longitude>
    <OpenTime>2024-10-08T02:40:16</OpenTime>
    <Description>Call regarding food support at 123 Main Street.</Description>
    <MaxCallTime>2024-10-08T15:40:16</MaxCallTime>
  </Call>
  <Call>
    <Id>1001</Id>
    <CallType>Other</CallType>
    <FullAddress>45 Elm Avenue</FullAddress>
    <Latitude>61.95596874944604</Latitude>
    <Longitude>-160.1818790203499</Longitude>
    <OpenTime>2024-08-26T23:09:16</OpenTime>
    <Description>Call regarding other support at 45 Elm Avenue.</Description>
    <MaxCallTime>2024-08-28T10:09:16</MaxCallTime>
  </Call>
  <Call>
    <Id>1002</Id>
    <CallType>Other</CallType>
    <FullAddress>78 Oak Lane</FullAddress>
    <Latitude>-64.37045284895437</Latitude>
    <Longitude>56.177561887278586</Longitude>
    <OpenTime>2024-06-01T16:47:16</OpenTime>
    <Description>Call regarding other support at 78 Oak Lane.</Description>
    <MaxCallTime>2024-06-02T03:47:16</MaxCallTime>
  </Call>
  <Call>
    <Id>1003</Id>
    <CallType>Food</CallType>
    <FullAddress>22 Maple Drive</FullAddress>
    <Latitude>-46.71741098087381</Latitude>
    <Longitude>-69.56392295094392</Longitude>
    <OpenTime>2023-07-07T16:25:16</OpenTime>
    <Description>Call regarding food support at 22 Maple Drive.</Description>
    <MaxCallTime>2023-07-08T09:25:16</MaxCallTime>
  </Call>
  <Call>
    <Id>1004</Id>
    <CallType>Technical</CallType>
    <FullAddress>56 Pine Boulevard</FullAddress>
    <Latitude>23.724513097857127</Latitude>
    <Longitude>158.39779529165565</Longitude>
    <OpenTime>2024-05-20T09:42:16</OpenTime>
    <Description>Call regarding technical support at 56 Pine Boulevard.</Description>
    <MaxCallTime>2024-05-20T12:42:16</MaxCallTime>
  </Call>
  <Call>
    <Id>1005</Id>
    <CallType>Technical</CallType>
    <FullAddress>89 Cedar Road</FullAddress>
    <Latitude>-2.9739177648152406</Latitude>
    <Longitude>-144.8077922141693</Longitude>
    <OpenTime>2024-03-18T10:20:16</OpenTime>
    <Description>Call regarding technical support at 89 Cedar Road.</Description>
    <MaxCallTime>2024-03-19T06:20:16</MaxCallTime>
  </Call>
  <Call>
    <Id>1006</Id>
    <CallType>Other</CallType>
    <FullAddress>101 Ash Street</FullAddress>
    <Latitude>54.11055511866999</Latitude>
    <Longitude>104.11797875755354</Longitude>
    <OpenTime>2024-09-07T20:37:16</OpenTime>
    <Description>Call regarding other support at 101 Ash Street.</Description>
    <MaxCallTime>2024-09-08T13:37:16</MaxCallTime>
  </Call>
  <Call>
    <Id>1007</Id>
    <CallType>Food</CallType>
    <FullAddress>ddd</FullAddress>
    <Latitude>44</Latitude>
    <Longitude>55</Longitude>
    <OpenTime>2005-12-12T20:20:20</OpenTime>
    <Description />
    <MaxCallTime xsi:nil="true" />
  </Call>
</ArrayOfCall>